macrometa_target_s3/__init__.py
macrometa_target_s3/constants.py
macrometa_target_s3/formats/__init__.py
macrometa_target_s3/formats/format_base.py
macrometa_target_s3/formats/format_csv.py
macrometa_target_s3/formats/format_json.py
macrometa_target_s3/formats/format_parquet.py
macrometa_target_s3/sinks.py
macrometa_target_s3/target.py
macrometa_target_s3-0.0.14.dist-info/entry_points.txt
macrometa_target_s3-0.0.14.dist-info/WHEEL
macrometa_target_s3-0.0.14.dist-info/METADATA
macrometa_target_s3-0.0.14.dist-info/RECORD
